snakeflake/__init__.py
snakeflake/config.py
snakeflake/exceptions.py
snakeflake/snakeflake.py
snakeflake/utils.py
snakeflake-0.1.5.2.dist-info/LICENSE
snakeflake-0.1.5.2.dist-info/METADATA
snakeflake-0.1.5.2.dist-info/WHEEL
snakeflake-0.1.5.2.dist-info/top_level.txt
snakeflake-0.1.5.2.dist-info/RECORD
