Metadata-Version: 2.1
Name: snakeflake
Version: 0.1.5.2
Summary: Snakeflake is a discrete nonserial ID generator like Snowflake implemented in Python
Home-page: https://github.com/Roadcrosser/snakeflake
Author: Roadcrosser
Author-email: roadcrosser0@gmail.com
License: Apache-2.0
Project-URL: Documentation, http://roadcrosser.xyz/snakeflake/
Project-URL: Source, https://github.com/Roadcrosser/snakeflake
Platform: UNKNOWN
Classifier: Programming Language :: Python :: 3
Classifier: License :: OSI Approved :: Apache Software License
Classifier: Operating System :: OS Independent
Requires-Python: >=3.6
